spacyfishing/__init__.py
spacyfishing/entity_fishing_linker.py
tests/__init__.py
tests/test_EF_component.py
spacyfishing-0.1.8.dist-info/LICENSE
spacyfishing-0.1.8.dist-info/METADATA
spacyfishing-0.1.8.dist-info/WHEEL
spacyfishing-0.1.8.dist-info/entry_points.txt
spacyfishing-0.1.8.dist-info/top_level.txt
spacyfishing-0.1.8.dist-info/RECORD
