Metadata-Version: 2.1
Name: spacyfishing
Version: 0.1.8
Summary: A spaCy wrapper of Entity-Fishing (component) for named entity disambiguation and linking on Wikidata.
Home-page: https://github.com/Lucaterre/spacyfishing
Author: Lucas Terriel
License: MIT
Keywords: spacy-extension,entity linking,entity disambiguation,nlp,natural language processing,entity-fishing
Classifier: License :: OSI Approved :: MIT License
Classifier: Intended Audience :: Developers
Classifier: Intended Audience :: Education
Classifier: Intended Audience :: Science/Research
Classifier: Operating System :: OS Independent
Classifier: Programming Language :: Python
Classifier: Programming Language :: Python :: 3.8
Classifier: Topic :: Software Development :: Libraries
Classifier: Topic :: Software Development :: Libraries :: Python Modules
Requires-Python: >=3.7
License-File: LICENSE
Requires-Dist: spacy (>=3.3.1)
Requires-Dist: requests (>=2.28.0)
